odoo/addons/product_template_tags/README.rst
odoo/addons/product_template_tags/__init__.py
odoo/addons/product_template_tags/__manifest__.py
odoo/addons/product_template_tags/i18n/de.po
odoo/addons/product_template_tags/i18n/es.po
odoo/addons/product_template_tags/i18n/fr.po
odoo/addons/product_template_tags/i18n/hr.po
odoo/addons/product_template_tags/i18n/it.po
odoo/addons/product_template_tags/i18n/nl.po
odoo/addons/product_template_tags/i18n/nl_NL.po
odoo/addons/product_template_tags/i18n/product_template_tags.pot
odoo/addons/product_template_tags/i18n/sl.po
odoo/addons/product_template_tags/models/__init__.py
odoo/addons/product_template_tags/models/product_template.py
odoo/addons/product_template_tags/models/product_template_tag.py
odoo/addons/product_template_tags/readme/CONFIGURE.rst
odoo/addons/product_template_tags/readme/CONTRIBUTORS.rst
odoo/addons/product_template_tags/readme/DESCRIPTION.rst
odoo/addons/product_template_tags/readme/USAGE.rst
odoo/addons/product_template_tags/security/product_template_rule.xml
odoo/addons/product_template_tags/security/product_template_tag.xml
odoo/addons/product_template_tags/static/description/icon.png
odoo/addons/product_template_tags/static/description/index.html
odoo/addons/product_template_tags/tests/__init__.py
odoo/addons/product_template_tags/tests/test_product_template_tags.py
odoo/addons/product_template_tags/views/product_product.xml
odoo/addons/product_template_tags/views/product_template.xml
odoo/addons/product_template_tags/views/product_template_tag.xml
odoo14_addon_product_template_tags-14.0.1.2.0.dist-info/METADATA
odoo14_addon_product_template_tags-14.0.1.2.0.dist-info/WHEEL
odoo14_addon_product_template_tags-14.0.1.2.0.dist-info/top_level.txt
odoo14_addon_product_template_tags-14.0.1.2.0.dist-info/RECORD
