Metadata-Version: 2.1
Name: odoo14-addon-product-template-tags
Version: 14.0.1.2.0
Summary: This addon allow to add tags on products
Home-page: https://github.com/OCA/product-attribute
Author: ACSONE SA/NV, Odoo Community Association (OCA), Numigi
Author-email: support@odoo-community.org
License: AGPL-3
Platform: UNKNOWN
Classifier: Programming Language :: Python
Classifier: Framework :: Odoo
Classifier: License :: OSI Approved :: GNU Affero General Public License v3
Requires-Python: >=3.6
Requires-Dist: odoo (<14.1dev,>=14.0a)
